edf_iron_client/__init__.py
edf_iron_client/__version__.py
edf_iron_client-2.0.0.dist-info/licenses/LICENSE
edf_iron_client-2.0.0.dist-info/METADATA
edf_iron_client-2.0.0.dist-info/WHEEL
edf_iron_client-2.0.0.dist-info/top_level.txt
edf_iron_client-2.0.0.dist-info/RECORD
