Metadata-Version: 2.4
Name: edf-iron-client
Version: 2.0.0
Summary: Iron Client
Author-email: CERT-EDF <cert@edf.fr>
License-Expression: MIT
Project-URL: Homepage, https://github.com/cert-edf/iron
Project-URL: Repository, https://github.com/cert-edf/iron
Project-URL: Bug Tracker, https://github.com/cert-edf/iron/issues
Keywords: edf,iron,client
Classifier: Development Status :: 5 - Production/Stable
Classifier: Intended Audience :: Developers
Classifier: Operating System :: OS Independent
Classifier: Programming Language :: Python :: 3
Classifier: Programming Language :: Python :: 3 :: Only
Classifier: Topic :: Utilities
Classifier: Topic :: Security
Requires-Python: >=3.12
License-File: LICENSE
Requires-Dist: edf-iron-core~=2.0
Dynamic: license-file
